{"cameraMode":{"drawMode":0,"name":"Shaded","section":"Shading Mode"},"sceneLighting":true,"audioPlay":false,"sceneViewState":{"m_AlwaysRefresh":false,"showFog":true,"showSkybox":true,"showFlares":true,"showImageEffects":true,"showParticleSystems":true,"showVisualEffectGraphs":true,"m_FxEnabled":true},"in2DMode":false,"pivot":{"x":0.2059386670589447,"y":-0.8620575666427612,"z":0.43162834644317629},"rotation":{"x":-0.4311859905719757,"y":0.0032455946784466507,"z":-0.0015510801458731294,"w":-0.9022564888000488},"size":1.9018381834030152,"orthographic":false}